minha_lib_screenshots/__init__.py
minha_lib_screenshots/core.py
minha_lib_screenshots/utils.py
minha_lib_screenshots-0.1.0.dist-info/licenses/LICENSE
minha_lib_screenshots-0.1.0.dist-info/METADATA
minha_lib_screenshots-0.1.0.dist-info/WHEEL
minha_lib_screenshots-0.1.0.dist-info/top_level.txt
minha_lib_screenshots-0.1.0.dist-info/RECORD
